rapticoressvc/__init__.py
rapticoressvc/epss_helper.py
rapticoressvc/helpers.py
rapticoressvc/kevc_helper.py
rapticoressvc/lambda_get_ssvc_recommendation.py
rapticoressvc/lambda_update_nvd.py
rapticoressvc/multi_threading_helper.py
rapticoressvc/nvd_data_helper.py
rapticoressvc/priority-options_v2.csv
rapticoressvc/risk_language_helper.py
rapticoressvc/ssvc_impact_options.csv
rapticoressvc/ssvc_ore.py
rapticoressvc/ssvc_utility_options.csv
rapticoressvc/svcc_constants.py
rapticoressvc/svcc_helper.py
rapticoressvc/vector_calculator_helpers.py
rapticoressvc/docs/conf.py
rapticoressvc/storage_helpers/files_helper.py
rapticoressvc/storage_helpers/s3_helper.py
rapticoressvc/test/__init__.py
rapticoressvc/test/kevc_helper_test.py
rapticoressvc/test/nvd_data_helper_test.py
rapticoressvc/test/s3_helper_test.py
rapticoressvc/test/ssvc_ore_test.py
rapticoressvc/test/test_data_helper.py
rapticoressvc/test/testing_helper.py
rapticoressvc-0.0.17.dist-info/licenses/LICENSE
rapticoressvc-0.0.17.dist-info/METADATA
rapticoressvc-0.0.17.dist-info/WHEEL
rapticoressvc-0.0.17.dist-info/entry_points.txt
rapticoressvc-0.0.17.dist-info/top_level.txt
rapticoressvc-0.0.17.dist-info/RECORD
