Metadata-Version: 2.4
Name: rapticoressvc
Version: 0.0.17
Summary: Rapticore SSVC
Author-email: Rapticore <ahsan.mir@rapticore.com>
License: MIT
Project-URL: Homepage, https://github.com/rapticore/ssvc_ore_miner
Project-URL: Bug Tracker, https://github.com/rapticore/ssvc_ore_miner/issues
Project-URL: Documentation, https://github.com/rapticore/ssvc_ore_miner#readme
Classifier: Programming Language :: Python :: 3
Classifier: Operating System :: OS Independent
Requires-Python: >=3.9
License-File: LICENSE
Requires-Dist: cvss
Requires-Dist: aws-lambda-powertools>=2.12.0
Requires-Dist: boto3>=1.26.110
Requires-Dist: nested_lookup
Requires-Dist: numpy<1.25.0,>=1.24.0
Requires-Dist: pandas<2.0.0,>=1.5.0
Requires-Dist: requests>=2.31.0
Requires-Dist: setuptools>=62.2.0
Requires-Dist: urllib3>=1.26.18
Requires-Dist: xlsxwriter>=3.0.8
Dynamic: license-file
